fake_focus/__init__.py
fake_focus-1.1.2.dist-info/WHEEL
fake_focus-1.1.2.dist-info/entry_points.txt
fake_focus-1.1.2.dist-info/METADATA
fake_focus-1.1.2.dist-info/RECORD
