Metadata-Version: 2.3
Name: fake-focus
Version: 1.1.2
Summary: Add your description here
Author: mayasnova
Author-email: mayasnova <mayas.nova.pro@gmail.com>
Requires-Dist: pyautogui>=0.9.54
Requires-Dist: pynput>=1.8.1
Requires-Dist: rich>=14.2.0
Requires-Python: >=3.8
